mLab_DopplerRadar/__init__.py
mLab_DopplerRadar/example_main.py
mLab_DopplerRadar/mLab_DopplerRadarTool.py
mLab_DopplerRadar/mLab_DopplerRadarTool_nocam.py
mLab_DopplerRadar/ui_pyqtgraph_rev2.py
mLab_DopplerRadar/ui_pyqtgraph_rev2_1.py
mLab_Doppler_Radar_Tool-0.1.5.7.dist-info/LICENSE
mLab_Doppler_Radar_Tool-0.1.5.7.dist-info/METADATA
mLab_Doppler_Radar_Tool-0.1.5.7.dist-info/WHEEL
mLab_Doppler_Radar_Tool-0.1.5.7.dist-info/top_level.txt
mLab_Doppler_Radar_Tool-0.1.5.7.dist-info/RECORD
