Metadata-Version: 2.1
Name: mLab-Doppler-Radar-Tool
Version: 0.1.5.7
Summary: mLab Doppler Radar UART tool and example code
Home-page: UNKNOWN
Author: Alex Kuan
Author-email: agathakuannew@gmail.com
License: MIT
Platform: UNKNOWN
Requires-Dist: pyserial
Requires-Dist: pyqtgraph
